veco/__init__.py
veco/__main__.py
veco-0.0.1a1.dist-info/METADATA
veco-0.0.1a1.dist-info/WHEEL
veco-0.0.1a1.dist-info/entry_points.txt
veco-0.0.1a1.dist-info/licenses/LICENSE
veco-0.0.1a1.dist-info/RECORD
